jupyter_hurl_kernel/__init__.py
jupyter_hurl_kernel/kernel.py
jupyter_hurl_kernel/labextension/package.json
jupyter_hurl_kernel/labextension/static/181.d421f0f584c50f575dea.js
jupyter_hurl_kernel/labextension/static/509.4e79c35edddd11573355.js
jupyter_hurl_kernel/labextension/static/remoteEntry.af4cc0330eb429a86f01.js
jupyter_hurl_kernel/labextension/static/style.js
jupyter_hurl_kernel/labextension/static/third-party-licenses.json
jupyter_hurl_kernel/labextension_src/.eslintrc.js
jupyter_hurl_kernel/labextension_src/.gitignore
jupyter_hurl_kernel/labextension_src/.npmignore
jupyter_hurl_kernel/labextension_src/.prettierrc
jupyter_hurl_kernel/labextension_src/.yarnrc.yml
jupyter_hurl_kernel/labextension_src/INSTALL.md
jupyter_hurl_kernel/labextension_src/LICENSE
jupyter_hurl_kernel/labextension_src/PUBLISHING.md
jupyter_hurl_kernel/labextension_src/README.md
jupyter_hurl_kernel/labextension_src/install.json
jupyter_hurl_kernel/labextension_src/jupyterlab_hurl_extension/__init__.py
jupyter_hurl_kernel/labextension_src/jupyterlab_hurl_extension/_version.py
jupyter_hurl_kernel/labextension_src/package-lock.json
jupyter_hurl_kernel/labextension_src/package.json
jupyter_hurl_kernel/labextension_src/pyproject.toml
jupyter_hurl_kernel/labextension_src/src/index.ts
jupyter_hurl_kernel/labextension_src/style/index.css
jupyter_hurl_kernel/labextension_src/style/index.js
jupyter_hurl_kernel/labextension_src/tsconfig.json
jupyter_hurl_kernel/labextension_src/yarn.lock
jupyter_hurl_kernel/resources/codemirror/hurl.js
jupyter_hurl_kernel/resources/kernel.json
jupyter_hurl_kernel-0.0.12.dist-info/WHEEL
jupyter_hurl_kernel-0.0.12.dist-info/entry_points.txt
jupyter_hurl_kernel-0.0.12.dist-info/METADATA
jupyter_hurl_kernel-0.0.12.dist-info/RECORD
