Metadata-Version: 2.3
Name: jupyter-hurl-kernel
Version: 0.0.12
Summary: A Jupyter kernel for running Hurl commands
Author: Cédric Couralet
Author-email: Cédric Couralet <cedric.couralet@insee.fr>
Requires-Dist: ipykernel>=6.29.0
Requires-Dist: jupyter-client>=8.6.0
Requires-Dist: jupyterlab>=4.0.0 ; extra == 'dev'
Requires-Python: >=3.13
Provides-Extra: dev
